snorq/__init__.py
snorq/alerts.py
snorq/config.py
snorq/consumer.py
snorq/exceptions.py
snorq/logging.py
snorq/main.py
snorq/producer.py
snorq/schemas.py
snorq/sniffer.py
snorq-0.2.2.dist-info/licenses/LICENSE.md
snorq-0.2.2.dist-info/METADATA
snorq-0.2.2.dist-info/WHEEL
snorq-0.2.2.dist-info/entry_points.txt
snorq-0.2.2.dist-info/top_level.txt
snorq-0.2.2.dist-info/RECORD
