Metadata-Version: 2.4
Name: snorq
Version: 0.2.2
Summary: Async URL sniffer and monitor
Author: Joe Gasewicz
Author-email: contact@josef.digital
Requires-Python: >=3.11
License-File: LICENSE.md
Requires-Dist: aiohttp>=3.8.0
Requires-Dist: colorlog>=6.7.0
Requires-Dist: aiosmtplib>=4.0.1
Requires-Dist: marshmallow>=4.0.0
Requires-Dist: click>=8.2.1
Dynamic: author
Dynamic: author-email
Dynamic: license-file
Dynamic: requires-dist
Dynamic: requires-python
Dynamic: summary
